OrderedFormat/__init__.py
OrderedFormat/formatter.py
OrderedFormat-0.0.2.dist-info/DESCRIPTION.rst
OrderedFormat-0.0.2.dist-info/METADATA
OrderedFormat-0.0.2.dist-info/RECORD
OrderedFormat-0.0.2.dist-info/WHEEL
OrderedFormat-0.0.2.dist-info/metadata.json
OrderedFormat-0.0.2.dist-info/top_level.txt
