Metadata-Version: 2.0
Name: OrderedFormat
Version: 0.0.2
Summary: Ordered value getter from Dictionary type value.
Home-page: https://github.com/Himenon/OrderedFormat
Author: K.Himeno
Author-email: k.himeno314@gmail.com
License: MIT
Keywords: ordered dictionary
Platform: UNKNOWN
Classifier: Development Status :: 3 - Alpha
Classifier: Programming Language :: Python :: 2.7
Classifier: Programming Language :: Python :: 3.5
Requires-Dist: pyyaml
Requires-Dist: six
Requires-Dist: yamlordereddictloader
